pollypocket/__init__.py
pollypocket/lagrange_interpolation.py
Pollypocket-0.1.0.dist-info/LICENSE
Pollypocket-0.1.0.dist-info/METADATA
Pollypocket-0.1.0.dist-info/WHEEL
Pollypocket-0.1.0.dist-info/top_level.txt
Pollypocket-0.1.0.dist-info/RECORD
