Metadata-Version: 2.1
Name: Pollypocket
Version: 0.1.0
Summary: A Python library for polynomial interpolation, including Lagrange interpolation.
Home-page: https://github.com/adechlien/pollypocket
Author: Alejandro J. Hernández P., Elvira E. Florez C., Vanessa Orozco M.
Author-email: 
License: MIT
Classifier: Programming Language :: Python :: 3
Classifier: License :: OSI Approved :: MIT License
Classifier: Operating System :: OS Independent
Requires-Python: >=3.10.2
License-File: LICENSE
Requires-Dist: sympy
